landlock/__init__.py
landlock/plumbing.py
landlock/porcelain.py
landlock-1.0.0.dev5.dist-info/licenses/LICENSE
landlock-1.0.0.dev5.dist-info/WHEEL
landlock-1.0.0.dev5.dist-info/METADATA
landlock-1.0.0.dev5.dist-info/RECORD
