Metadata-Version: 2.4
Name: landlock
Version: 1.0.0.dev5
Summary: Python interface to the Landlock Linux Security Module.
Author-email: Edward Knight <edw@rdknig.ht>
Requires-Python: >=3.9
Classifier: Development Status :: 3 - Alpha
Classifier: Intended Audience :: Developers
Classifier: License :: OSI Approved :: MIT License
Classifier: Natural Language :: English
Classifier: Operating System :: POSIX :: Linux
Classifier: Programming Language :: Python :: 3 :: Only
Classifier: Topic :: Security
Classifier: Topic :: Software Development :: Libraries :: Python Modules
Classifier: Topic :: System :: Operating System Kernels :: Linux
License-File: LICENSE
Requires-Dist: build ~= 1.2 ; extra == "deploy"
Requires-Dist: twine ~= 6.1 ; extra == "deploy"
Requires-Dist: pre-commit ~= 4.2 ; extra == "dev"
Requires-Dist: landlock[test] ; extra == "dev"
Requires-Dist: pytest ~= 8.3 ; extra == "test"
Requires-Dist: pytest-cov ~= 6.1 ; extra == "test"
Requires-Dist: pytest-forked ~= 1.6  ; extra == "test" and ( sys_platform != 'win32')
Project-URL: Home, https://github.com/Edward-Knight/landlock
Provides-Extra: deploy
Provides-Extra: dev
Provides-Extra: test
